<?xml version='1.0' encoding='utf-8'?>
<!DOCTYPE hibernate-mapping PUBLIC
    "-//Hibernate/Hibernate Mapping DTD 3.0//EN"
    "http://www.hibernate.org/dtd/hibernate-mapping-3.0.dtd">
<hibernate-mapping>

    <class name="com.scottishwitchcraft.webapi.models.Reference" table="wdb_reference" schema="public"
           catalog="ScottishWitchcraft.Dev">
        <id name="referenceref">
            <column name="referenceref" sql-type="char(50)" length="50"/>
        </id>
        <property name="refsystemid">
            <column name="refsystemid" sql-type="char(50)" length="50" not-null="true"/>
        </property>
        <property name="referenceid">
            <column name="referenceid" sql-type="bigint" not-null="true"/>
        </property>
        <property name="reference">
            <column name="reference" sql-type="char(255)" not-null="true"/>
        </property>
        <property name="kirksession">
            <column name="kirksession" sql-type="boolean" not-null="true"/>
        </property>
        <property name="presbytery">
            <column name="presbytery" sql-type="boolean" not-null="true"/>
        </property>
        <property name="burghcourt">
            <column name="burghcourt" sql-type="boolean" not-null="true"/>
        </property>
        <property name="confession">
            <column name="confession" sql-type="boolean" not-null="true"/>
        </property>
        <property name="draftdittay">
            <column name="draftdittay" sql-type="boolean" not-null="true"/>
        </property>
        <property name="commCourtmin">
            <column name="comm_courtmin" sql-type="boolean" not-null="true"/>
        </property>
        <property name="justCourtmin">
            <column name="just_courtmin" sql-type="boolean" not-null="true"/>
        </property>
        <property name="circuitCourtmin">
            <column name="circuit_courtmin" sql-type="boolean" not-null="true"/>
        </property>
        <property name="dittay">
            <column name="dittay" sql-type="boolean" not-null="true"/>
        </property>
        <property name="pleadings">
            <column name="pleadings" sql-type="boolean" not-null="true"/>
        </property>
        <property name="witdep">
            <column name="witdep" sql-type="boolean" not-null="true"/>
        </property>
        <property name="witstatement">
            <column name="witstatement" sql-type="boolean" not-null="true"/>
        </property>
        <property name="commjust">
            <column name="commjust" sql-type="boolean" not-null="true"/>
        </property>
        <property name="privycouncil">
            <column name="privycouncil" sql-type="boolean" not-null="true"/>
        </property>
        <property name="parliament">
            <column name="parliament" sql-type="boolean" not-null="true"/>
        </property>
        <property name="estates">
            <column name="estates" sql-type="boolean" not-null="true"/>
        </property>
        <property name="royal">
            <column name="royal" sql-type="boolean" not-null="true"/>
        </property>
        <property name="commtext">
            <column name="commtext" sql-type="boolean" not-null="true"/>
        </property>
        <property name="verdict">
            <column name="verdict" sql-type="boolean" not-null="true"/>
        </property>
        <property name="sentence">
            <column name="sentence" sql-type="boolean" not-null="true"/>
        </property>
        <property name="chronicle">
            <column name="chronicle" sql-type="boolean" not-null="true"/>
        </property>
        <property name="financial">
            <column name="financial" sql-type="boolean" not-null="true"/>
        </property>
        <property name="other">
            <column name="other" sql-type="char(50)" length="50" not-null="true"/>
        </property>
        <property name="notes">
            <column name="notes" sql-type="text" not-null="true"/>
        </property>
        <property name="createdby">
            <column name="createdby" sql-type="char(50)" length="50" not-null="true"/>
        </property>
        <property name="createdate">
            <column name="createdate" sql-type="date" not-null="true"/>
        </property>
        <property name="lastupdatedby">
            <column name="lastupdatedby" sql-type="char(50)" length="50" not-null="true"/>
        </property>
        <property name="lastupdatedon">
            <column name="lastupdatedon" sql-type="date" not-null="true"/>
        </property>
        <many-to-one name="wdbCaseByCaseref" class="com.scottishwitchcraft.webapi.data.models.Case">
            <column name="caseref" not-null="true"/>
        </many-to-one>
        <many-to-one name="wdbSourceBySourceref" class="com.scottishwitchcraft.webapi.models.Source">
            <column name="sourceref" not-null="true"/>
        </many-to-one>
    </class>
</hibernate-mapping>